spacegpt/__init__.py
spacegpt/catalog/__init__.py
spacegpt/driver/__init__.py
spacegpt/driver/handler.py
spacegpt/intent/__init__.py
SpaceGPT-0.0.1.dist-info/LICENSE
SpaceGPT-0.0.1.dist-info/METADATA
SpaceGPT-0.0.1.dist-info/WHEEL
SpaceGPT-0.0.1.dist-info/top_level.txt
SpaceGPT-0.0.1.dist-info/RECORD
